<?xml version="1.0" encoding="UTF-8"?>
<internal-compliance-request>
  <admin>
    <subscriber-password></subscriber-password>
    <order-keys>
      <sz-order-type></sz-order-type>
      <mn-order-number negative="false" decimal-position="0"
                       currency-decimals="0" zero="true">
        <currency-code></currency-code>
        <value>0</value>
      </mn-order-number>
      <CDenialFlagYN></CDenialFlagYN>
      <sz-order-company></sz-order-company>
    </order-keys>
    <included-request></included-request>
    <subscriber-id></subscriber-id>
    <ticket></ticket>
    <comments></comments>
    <output-format></output-format>
    <request-date>2013-09-18T16:48:16.977-04:00</request-date>
  </admin>
  <transaction>
    <party-screening></party-screening>
    <user-defined></user-defined>
    <classifier>
      <label></label>
      <type></type>
      <classification>
        <label></label>
        <type></type>
      </classification>
    </classifier>
    <classifier>
      <label></label>
      <type></type>
      <classification>
        <label></label>
        <type></type>
      </classification>
    </classifier>
    <transaction-date>2013-09-18T16:48:16.978-04:00</transaction-date>
    <type></type>
    <version></version>
    <ship-from-country>
      <ship-from>
        <code></code>
        <schema></schema>
        <domain></domain>
      </ship-from>
    </ship-from-country>
    <parameters>
      <threshold></threshold>
      <exact-match></exact-match>
      <red-flag></red-flag>
      <country-match></country-match>
    </parameters>
    <comments></comments>
    <license-screening></license-screening>
    <deploy-mode></deploy-mode>
    <party>
      <postal-code></postal-code>
      <state></state>
      <name></name>
      <fax></fax>
      <country>
        <code></code>
        <schema></schema>
        <domain></domain>
      </country>
      <end-user-type></end-user-type>
      <addresses></addresses>
      <end-user-party>
        <end-user-certificate></end-user-certificate>
        <non-uSGovernment></non-uSGovernment>
        <military></military>
        <end-user></end-user>
        <descriptor>
          <type></type>
          <attribute>
            <type></type>
            <value></value>
          </attribute>
          <attribute>
            <type></type>
            <value></value>
          </attribute>
        </descriptor>
        <descriptor>
          <type></type>
          <attribute>
            <type></type>
            <value></value>
          </attribute>
          <attribute>
            <type></type>
            <value></value>
          </attribute>
        </descriptor>
      </end-user-party>
      <city></city>
      <contact></contact>
      <phone></phone>
      <email></email>
      <type></type>
      <user-defined></user-defined>
    </party>
    <party>
      <postal-code></postal-code>
      <state></state>
      <name></name>
      <fax></fax>
      <country>
        <code></code>
        <schema></schema>
        <domain></domain>
      </country>
      <end-user-type></end-user-type>
      <addresses></addresses>
      <end-user-party>
        <end-user-certificate></end-user-certificate>
        <non-uSGovernment></non-uSGovernment>
        <military></military>
        <end-user></end-user>
        <descriptor>
          <type></type>
          <attribute>
            <type></type>
            <value></value>
          </attribute>
          <attribute>
            <type></type>
            <value></value>
          </attribute>
        </descriptor>
        <descriptor>
          <type></type>
          <attribute>
            <type></type>
            <value></value>
          </attribute>
          <attribute>
            <type></type>
            <value></value>
          </attribute>
        </descriptor>
      </end-user-party>
      <city></city>
      <contact></contact>
      <phone></phone>
      <email></email>
      <type></type>
      <user-defined></user-defined>
    </party>
    <descriptor>
      <type></type>
      <attribute>
        <type></type>
        <value></value>
      </attribute>
      <attribute>
        <type></type>
        <value></value>
      </attribute>
    </descriptor>
    <descriptor>
      <type></type>
      <attribute>
        <type></type>
        <value></value>
      </attribute>
      <attribute>
        <type></type>
        <value></value>
      </attribute>
    </descriptor>
    <date-format></date-format>
    <language></language>
    <transaction-line>
      <party>
        <postal-code></postal-code>
        <state></state>
        <name></name>
        <id></id>
        <fax></fax>
        <country>
          <code></code>
          <schema></schema>
          <domain></domain>
        </country>
        <end-user-type></end-user-type>
        <addresses></addresses>
        <end-user-party></end-user-party>
        <city></city>
        <contact></contact>
        <phone></phone>
        <email></email>
        <type></type>
        <user-defined></user-defined>
      </party>
      <user-defined></user-defined>
      <product>
        <end-use-type></end-use-type>
        <encryption></encryption>
        <product-id></product-id>
        <license-exception></license-exception>
        <value></value>
        <country-origin>
          <code></code>
          <schema></schema>
          <domain></domain>
        </country-origin>
        <classifier>
          <label></label>
          <type></type>
          <classification>
            <label></label>
            <type></type>
          </classification>
        </classifier>
      </product>
    </transaction-line>
    <transaction-line>
      <party>
        <postal-code></postal-code>
        <state></state>
        <name></name>
        <id></id>
        <fax></fax>
        <country>
          <code></code>
          <schema></schema>
          <domain></domain>
        </country>
        <end-user-type></end-user-type>
        <addresses></addresses>
        <end-user-party></end-user-party>
        <city></city>
        <contact></contact>
        <phone></phone>
        <email></email>
        <type></type>
        <user-defined></user-defined>
      </party>
      <user-defined></user-defined>
      <product>
        <end-use-type></end-use-type>
        <encryption></encryption>
        <product-id></product-id>
        <license-exception></license-exception>
        <value></value>
        <country-origin>
          <code></code>
          <schema></schema>
          <domain></domain>
        </country-origin>
        <classifier>
          <label></label>
          <type></type>
          <classification>
            <label></label>
            <type></type>
          </classification>
        </classifier>
      </product>
    </transaction-line>
    <request-date>2013-09-18T16:48:16.979-04:00</request-date>
    <embargo-screening></embargo-screening>
    <ship-to-country>
      <ship-to>
        <code></code>
        <schema></schema>
        <domain></domain>
      </ship-to>
    </ship-to-country>
    <ticket></ticket>
  </transaction>
</internal-compliance-request>